ushka-0.0.5.dist-info/METADATA
ushka-0.0.5.dist-info/WHEEL
ushka-0.0.5.dist-info/entry_points.txt
ushka-0.0.5.dist-info/licenses/LICENSE
ushka/__init__.py
ushka/application.py
ushka/http/request.py
ushka/http/response.py
ushka/routing/router.py
ushka-0.0.5.dist-info/RECORD
