Metadata-Version: 2.1
Name: ushka
Version: 0.0.5
Summary: Ushka is a minimal, experimental Python micro-framework for hobbyists and solo developers. Its goal is to enable rapid API development with zero boilerplate by using file-based routing.
Keywords: web,framework,asgi,routing,autodiscovery
Author-Email: kleber-code <kleber.code@gmail.com>
License: MIT
Classifier: Development Status :: 3 - Alpha
Classifier: Programming Language :: Python :: 3
Classifier: Programming Language :: Python :: 3.10
Classifier: Programming Language :: Python :: 3.11
Classifier: Programming Language :: Python :: 3.12
Classifier: License :: OSI Approved :: MIT License
Classifier: Framework :: AsyncIO
Classifier: Intended Audience :: Developers
Classifier: Operating System :: OS Independent
Classifier: Topic :: Internet :: WWW/HTTP
Classifier: Topic :: Software Development :: Libraries :: Application Frameworks
Project-URL: Homepage, https://github.com/kleber-code/ushka
Project-URL: Issues, https://github.com/kleber-code/ushka/issues
Project-URL: Repository, https://github.com/kleber-code/ushka
Requires-Python: >=3.10
Requires-Dist: uvicorn>=0.38.0
